setup.py
piledmatrix/__init__.py
piledmatrix/directions.py
piledmatrix.egg-info/PKG-INFO
piledmatrix.egg-info/SOURCES.txt
piledmatrix.egg-info/dependency_links.txt
piledmatrix.egg-info/not-zip-safe
piledmatrix.egg-info/top_level.txt