Metadata-Version: 1.1
Name: piledmatrix
Version: 1.0.0
Summary: Python library for RaspberryPi for interfacing LED matrix array with MAX7219 chip.
Home-page: https://github.com/jonayet/piledmatrix
Author: Jonayet Hossain
Author-email: jonayet.bu@gmail.com
License: MIT
Download-URL: https://github.com/jonayet/piledmatrix/tarball/1.0.0
Platform: raspberry-pi
